aiohttp_session_file/__init__.py
aiohttp_session_file-0.0.3.dist-info/METADATA
aiohttp_session_file-0.0.3.dist-info/WHEEL
aiohttp_session_file-0.0.3.dist-info/top_level.txt
aiohttp_session_file-0.0.3.dist-info/RECORD
