Metadata-Version: 2.1
Name: aiohttp-session-file
Version: 0.0.3
Summary: file sessions for aiohttp.web
Home-page: https://github.com/zhangkaizhao/aiohttp-session-file
Author: Kaizhao Zhang
Author-email: zhangkaizhao@gmail.com
License: Apache 2
Platform: UNKNOWN
Classifier: License :: OSI Approved :: Apache Software License
Classifier: Intended Audience :: Developers
Classifier: Programming Language :: Python
Classifier: Programming Language :: Python :: 3
Classifier: Programming Language :: Python :: 3.5
Classifier: Programming Language :: Python :: 3.6
Classifier: Programming Language :: Python :: 3.7
Classifier: Topic :: Internet :: WWW/HTTP
Classifier: Framework :: AsyncIO
Requires-Python: >=3.5
Requires-Dist: aiohttp-session
Requires-Dist: aiofiles
